pysan/__init__.py
pysan/_nbdev.py
pysan/attributes.py
pysan/core.py
pysan/derivatives.py
pysan/editdistances.py
pysan/elements.py
pysan/multi.py
pysan/ngrams.py
pysan/nonalignment.py
pysan/spelldistances.py
pysan/spells.py
pysan/statistics.py
pysan/subsequences.py
pysan/transitions.py
pysan/wholecomparison.py
pysan-0.2.4.dist-info/LICENSE
pysan-0.2.4.dist-info/METADATA
pysan-0.2.4.dist-info/WHEEL
pysan-0.2.4.dist-info/entry_points.txt
pysan-0.2.4.dist-info/top_level.txt
pysan-0.2.4.dist-info/RECORD
