Metadata-Version: 2.1
Name: pysan
Version: 0.2.4
Summary: Sequence Analysis in Python
Home-page: https://github.com/pysan-dev/pysan/tree/master/
Author: Oliver J. Scholten
Author-email: oliver@gamba.dev
License: Apache Software License 2.0
Keywords: sequence analysis python
Platform: UNKNOWN
Classifier: Development Status :: 3 - Alpha
Classifier: Intended Audience :: Developers
Classifier: License :: OSI Approved :: Apache Software License
Classifier: Natural Language :: English
Classifier: Programming Language :: Python :: 3.6
Classifier: Programming Language :: Python :: 3.7
Classifier: Programming Language :: Python :: 3.8
Requires-Python: >=3.6
License-File: LICENSE
Requires-Dist: matplotlib (>=3.3.1)
Requires-Dist: pandas (>=1.0.5)
